req_queue.sv
module req_queue (
	input wire [21:0] queue_in,
	input wire clk, rst, write_en, mem_ready, 
    input wire [3:0] rownum,
	output reg [13:0] queue_data,
	output full_sig, empty_sig //not reg because we just need it as a wire assigning values
);

	parameter DEPTH = 8;
	parameter WIDTH = 22;
	parameter ADDR_SIZE = $clog2(DEPTH);
	reg [WIDTH-1:0] schedulerQ [0:DEPTH-1];
	reg fifo_empty = 0;
    reg fifo_full = 0;
	reg [ADDR_SIZE:0] count = 0;
	reg [ADDR_SIZE-1:0] rd_ptr = 0,wr_ptr = 0;
	
	

	always@(posedge clk or negedge rst) begin
		if(!rst) begin
			wr_ptr <= 0;
			rd_ptr <= 0;
			queue_data <= 0;
            count <= 0;
		end else begin
            //READ FROM THE QUEUE
			if(!write_en && !fifo_empty && mem_ready) begin
		//		queue_data <= {[10:9]schedulerQ[rd_ptr],[15:14]schedulerQ[rd_ptr],[21:14]schedulerQ[rd_ptr],[12:9]schedulerQ[rd_ptr]};
		//		rd_ptr <= rd_ptr+1;
				count <= count-1;
            //WRITE INTO THE QUEUE
			end else if (write_en && !fifo_full) begin
				schedulerQ[wr_ptr] <= queue_in;
				wr_ptr <= wr_ptr+1;
				count <= count+1;
			end
		end
	end

	always@(*) begin
		if(count == 0) begin
			fifo_empty = 1;
		end
		else if (count[ADDR_SIZE]==1) begin	
			fifo_full = 1;
		end
        else begin
            fifo_empty = 0;
            fifo_full = 0;
        end
	end
	assign full_sig = fifo_full;
	assign empty_sig = fifo_empty;


    //FSM Part
    always@(posedge clk) begin
		if(!write_en && !fifo_empty && mem_ready) begin
			queue_data <= {schedulerQ[rd_ptr][8],schedulerQ[rd_ptr][13],schedulerQ[rd_ptr][21:14],schedulerQ[rd_ptr][12:9]};
			rd_ptr <= rd_ptr+1;
         //   count <= count-1;
        end
    end

endmodule

tb/req_queue_tb.sv
module req_queue_tb;

reg [21:0] queue_in;
reg clk, rst, write_en, mem_ready;
reg [3:0] rownum;
wire [13:0] queue_data;
wire full_sig, empty_sig;

req_queue r1(
    .queue_in(queue_in),
    .clk(clk),
    .rst(rst),
    .write_en(write_en),
    .mem_ready(mem_ready),
    .rownum(rownum),
    .queue_data(queue_data),
    .full_sig(full_sig),
    .empty_sig(empty_sig)
);


always #5 clk = ~clk;

initial begin
    rst = 0;
    rownum = 4'b1010;
    write_en = 1;
    clk = 0;
    #10 rst = 1;
    mem_ready = 0;
end
initial begin
    #100 write_en = 0;
end
initial begin
    repeat(10) begin
        queue_in = $urandom;
//        mem_ready = $urandom;
        #10;
    end
end
initial begin
    //$monitor("Time: %0t, Clock: %0b, Queue Data: %0d, Full_Sig: %0b, Empty_Sig: %0b",$time, clk, queue_data, full_sig, empty_sig);
end
initial begin
    $monitor("Time: %0t, \t Write: %0b, \t Queue In: %0d, \t Mem_Ready: %0b, \t Queue Data: %0d, \t Full_Sig: %0b, \t Empty_Sig: %0b",
              $time, write_en, queue_in, mem_ready, queue_data, full_sig, empty_sig);
end
initial begin
    //$monitor("Time: %0t, Queue In: %0d, Enable: %0b, Mem_Ready: %0b",$time, queue_in, write_en, mem_ready);
end
initial begin
    #200 $finish;
end
initial begin
    $dumpfile("req_queue.vcd");
    $dumpvars(0,req_queue_tb);
end
endmodule

tb/req_queue.vcd
$date
	Fri Aug 14 11:50:57 2026
$end
$version
	Icarus Verilog
$end
$timescale
	1s
$end
$scope module req_queue_tb $end
$var wire 14 ! queue_data [13:0] $end
$var wire 1 " full_sig $end
$var wire 1 # empty_sig $end
$var reg 1 $ clk $end
$var reg 1 % mem_ready $end
$var reg 22 & queue_in [21:0] $end
$var reg 4 ' rownum [3:0] $end
$var reg 1 ( rst $end
$var reg 1 ) write_en $end
$scope module r1 $end
$var wire 1 $ clk $end
$var wire 1 * fifo_full $end
$var wire 1 " full_sig $end
$var wire 1 % mem_ready $end
$var wire 22 + queue_in [21:0] $end
$var wire 4 , rownum [3:0] $end
$var wire 1 ( rst $end
$var wire 1 ) write_en $end
$var wire 1 - fifo_empty $end
$var wire 1 # empty_sig $end
$var parameter 32 . ADDR_SIZE $end
$var parameter 32 / DEPTH $end
$var parameter 32 0 WIDTH $end
$var reg 4 1 count [3:0] $end
$var reg 14 2 queue_data [13:0] $end
$var reg 3 3 rd_ptr [2:0] $end
$var reg 3 4 wr_ptr [2:0] $end
$upscope $end
$upscope $end
$enddefinitions $end
$comment Show the parameter values. $end
$dumpall
b10110 0
b1000 /
b11 .
$end
#0
$dumpvars
b0 4
b0 3
b0 2
b0 1
1-
b1010 ,
b101010011010100100100 +
0*
1)
0(
b1010 '
b101010011010100100100 &
x%
0$
1#
0"
b0 !
$end
#5
1$
#10
0$
b10010101111010000001 &
b10010101111010000001 +
0%
1(
#15
0#
0-
b1 1
b1 4
1$
#20
0$
b1001101011000001001 &
b1001101011000001001 +
#25
b10 1
b10 4
1$
#30
0$
b1100000101011001100011 &
b1100000101011001100011 +
#35
b11 1
b11 4
1$
#40
0$
b1110010111101100001101 &
b1110010111101100001101 +
#45
b100 1
b100 4
1$
#50
0$
b111111001100110001101 &
b111111001100110001101 +
#55
b101 1
b101 4
1$
#60
0$
b101000010001100101 &
b101000010001100101 +
#65
b110 1
b110 4
1$
#70
0$
b1101110101001000010010 &
b1101110101001000010010 +
#75
b111 1
b111 4
1$
#80
0$
b1100111110001100000001 &
b1100111110001100000001 +
#85
1"
1*
b1000 1
b0 4
1$
#90
0$
b101111100110100001101 &
b101111100110100001101 +
#95
1$
#100
0$
0)
